LICENSE
MANIFEST.in
README.md
setup.py
djutils/__init__.py
djutils/date_utils.py
djutils/forms.py
djutils/graphite.py
djutils/json_utils.py
djutils/middleware.py
djutils/models.py
djutils/response.py
djutils/testrunner.py
djutils/widgets.py
djutils/management/__init__.py
djutils/management/commands/__init__.py
djutils/management/commands/pretty_dumpdata.py
djutils/static/djutils/js/capitalize.js
djutils/templates/djutils/sort_th.html
djutils/templatetags/__init__.py
djutils/templatetags/djutils.py
djutils/tests/__init__.py
djutils/tests/test_rest_auth.py
djutils/views/__init__.py
djutils/views/generic.py
djutils/views/helpers.py
djutils/views/rest_auth.py
sw_django_utils.egg-info/PKG-INFO
sw_django_utils.egg-info/SOURCES.txt
sw_django_utils.egg-info/dependency_links.txt
sw_django_utils.egg-info/requires.txt
sw_django_utils.egg-info/top_level.txt