Metadata-Version: 1.0
Name: sw-django-utils
Version: 0.0.53
Summary: Soft Way company django utils.
Home-page: https://github.com/telminov/sw-django-utils
Author: Telminov Sergey
Author-email: sergey@telminov.ru
License: The MIT License
Platform: UNKNOWN
